{
  "text_block_list": [
    {
      "name": "Winning Ticket",
      "text": "Hayahide! Happyyy birthdaaay!"
    },
    {
      "name": "Narita Taishin",
      "text": "…Happy birthday."
    },
    {
      "name": "Biwa Hayahide",
      "text": "Heh, thank you. Getting to spend \nanother birthday with you two is all \nI could ever ask for."
    },
    {
      "name": "Winning Ticket",
      "text": "If you think about it, you're Brian's older \nsister, but you're also the older sister \nout of the three of us, too!"
    },
    {
      "name": "Winning Ticket",
      "text": "Oh, I know! For the rest of the day, \nI'm gonna call you \"big sis\"!"
    },
    {
      "name": "Biwa Hayahide",
      "text": "…?!"
    },
    {
      "name": "Winning Ticket",
      "text": "Ah, you like that? You do, don't you? \nWoohoo! C'mon, you do it too, Taishin!"
    },
    {
      "name": "Narita Taishin",
      "text": "Huh? Not a chance!"
    },
    {
      "name": "Winning Ticket",
      "text": "Why nooot? You don't like \"big sis\"? \nWhat about just \"sis\"? \"Big sister\"? \n\"Dearest sister\"?!"
    },
    {
      "name": "Narita Taishin",
      "text": "That's not what I mean! \nFirst of all, why would \"big sis\" be ——"
    },
    {
      "name": "Biwa Hayahide",
      "text": "……!!!"
    },
    {
      "name": "Narita Taishin",
      "text": "Stop reacting to it, idiot!"
    }
  ],
  "no_wrap": true
}