{
  "text_block_list": [
    {
      "name": "Ines Fujin",
      "text": "<i>Sigh…</i> It was such an important opportunity.\nI can't believe I couldn't stay in front."
    },
    {
      "name": "Ines Fujin",
      "text": "I wonder… Should I come up with a strategy\nfor when my opponents surge ahead late or\nchase me down at the very end…?"
    },
    {
      "name": "Twin Turbo",
      "text": "Whaaaat?!"
    },
    {
      "name": "Twin Turbo",
      "text": "Just outrun them even more next time!\nGoing full turbo's always the way to do it!!"
    },
    {
      "name": "Silence Suzuka",
      "text": "I'd have to agree."
    },
    {
      "name": "Silence Suzuka",
      "text": "I never want to give up the view from the very\nfront… Is it different for you, Ines?"
    },
    {
      "name": "Ines Fujin",
      "text": "No, you're right… I want to stay ahead\nof the pack too!"
    },
    {
      "name": "Ines Fujin",
      "text": "Thanks, you two! I feel like I can try\neven harder now!"
    },
    {
      "name": "Ines Fujin",
      "text": "Yeah! There's no way I'll miss out\nat the next kids' clothing sale!"
    },
    {
      "name": "Both",
      "text": "Huh?!"
    }
  ],
  "no_wrap": true
}