{
  "title": "Teacher and Student",
  "no_wrap": true,
  "text_block_list": [
    {
      "name": "Caster Umamusume",
      "text": "Everyone! The time has finally come… \n…For the last event of the day, the relay race!!"
    },
    {
      "name": "Caster Umamusume",
      "text": "The rules are very simple! The relay begins with a 1200 meter \nleg, then 1600 meters, and 2000 meters! Each leg's assigned \nracer will pass the baton to their teammate for the next——"
    },
    {
      "name": "Caster Umamusume",
      "text": "Until the very end, where the team captains will \nface off on a 2400 meter track!!"
    },
    {
      "name": "Caster Umamusume",
      "text": "The total points each team earned throughout today's events \nare almost the same!! It all comes down to this relay race!!"
    },
    {
      "name": "Jungle Pocket",
      "text": "Fuji Kiseki."
    },
    {
      "name": "Jungle Pocket",
      "text": "Come on. We're gonna have an all-out battle! Me and you!"
    },
    {
      "name": "Fuji Kiseki",
      "text": "………………Heh heh."
    },
    {
      "name": "Fuji Kiseki",
      "text": "All right then. Shall we? \n——My cute little Pokke."
    },
    {
      "name": "Caster Umamusume",
      "text": "All the competitors have taken their places, and our starters \nare on their marks for the first leg of the relay! \n……And they're off!!"
    },
    {
      "name": "Caster Umamusume",
      "text": "——The white team's second racer Agnes Digital is slowly \nbut steadily extending her lead!! She showed what she could \ndo on 2000 meters, and she's every bit as heroic on 1600!!"
    },
    {
      "name": "Agnes Digital",
      "text": "Huff, huff, huff—— \nSorry to keep you waiting, Tachyon-saaaaaan!!"
    },
    {
      "name": "Agnes Tachyon",
      "text": "I'll be going on ahead, Tap-kun."
    },
    {
      "name": "Tap Dance City",
      "text": "Ahead, huh? Heh. Say, Digital… \nI know this tiny lead ain't the best you can do."
    },
    {
      "name": "Tap Dance City",
      "text": "I might've lost our race, but it looks like I really \ntook it outta you. So—— <i>This is our chance!</i>"
    },
    {
      "name": "Agnes Tachyon",
      "text": "(Let's see… The experiment's running smoothly. I suppose \nI could show some restraint. All I need to do is set the stage \nfor Fuji-kun to put on a splendid performance. But——)"
    },
    {
      "name": "Tap Dance City",
      "text": "Graaaaaaaaaaaaaah!! \nGet ready, Cap'n!!"
    },
    {
      "name": "Agnes Tachyon",
      "text": "(It seems the concept of \"restraint\" means nothing to you all. \nHonestly, you are all incorrigible——)"
    },
    {
      "name": "Agnes Tachyon",
      "text": "Have some sympathy, why don't you! How do you think I feel \nevery time you force me to the limit——!?"
    },
    {
      "name": "Caster Umamusume",
      "text": "Storming down the third leg, it's the white team's Agnes Tachyon \nand the red team's Tap Dance City!! They're neck and neck! \nIt's a dead heat!! And…!!"
    },
    {
      "name": "Tap & Tachyon",
      "text": "GO!"
    },
    {
      "name": "Fuji & Pokke",
      "text": "HHAAAAAAAAAAAAAH!! \nGRAAAAAAAAAAAHHH!!"
    },
    {
      "name": "Caster Umamusume",
      "text": "And now they've passed the batons to their captains!! \nJungle Pocket and Fuji Kiseki break through into the \nfinal leeeeeeg!!"
    },
    {
      "name": "Jungle Pocket",
      "text": "I wanna win… I wanna win, I wanna win! I wanna beat you!! \nYour back showed me the way for so long… And now… \nI wanna pass it!!"
    },
    {
      "name": "Jungle Pocket",
      "text": "So I can let you look at MY back… \nAnd see how much I've grown!!"
    },
    {
      "name": "Jungle Pocket",
      "text": "So you can see just how much you've done for me! \nAnd look ahead at me with pride!!"
    },
    {
      "name": "Fuji Kiseki",
      "text": "No! I won't. I won't leave your sight. \nI can still keep showing you the way! \nI won't let anything make me stop!"
    },
    {
      "name": "Fuji Kiseki",
      "text": "Please, don't thank me. Don't say a thing. \nCan't you see just how much you've given me all along?"
    },
    {
      "name": "Fuji Kiseki",
      "text": "That's why I can't let you pass me. Not yet. \nNot when there's still so much more for me to give you. \nSo much more of me for you to see!"
    },
    {
      "name": "Caster Umamusume",
      "text": "They turn the corner and enter the home stretch! \nFuji Kiseki in the lead! Jungle Pocket in hot pursuit!"
    },
    {
      "name": "Jungle Pocket",
      "text": "We're not done yet!! \nMy race is just getting started!!"
    },
    {
      "name": "Jungle Pocket",
      "text": "I am going to beat you… FUJI KISEKI!!"
    },
    {
      "name": "Fuji Kiseki",
      "text": "No…!! \nI'm not losing to you… JUNGLE POCKET!!"
    },
    {
      "name": "Fuji & Pokke",
      "text": "HAAAAAAAAAAAAAAHHH!!"
    },
    {
      "name": "Caster Umamusume",
      "text": "THEY CROSS THE FINISH LIIIIIINE!! \nThe winner of the relay race is…!! By a neck——"
    },
    {
      "name": "Caster Umamusume",
      "text": "Fuji Kiseki takes it!! \nThe winner is the white teeeeaaaaaaaaaam!!"
    },
    {
      "name": "Jungle Pocket",
      "text": "————Huff… Huff… \nAww…"
    },
    {
      "name": "Jungle Pocket",
      "text": "……Dammit… \nYou're so tough…!!!!"
    },
    {
      "name": "Jungle Pocket",
      "text": "Haha—— \n…………You really are… so damn awesome——"
    },
    {
      "name": "Fuji Kiseki",
      "text": "Hahaha…! Of course I am."
    },
    {
      "name": "Fuji Kiseki",
      "text": "I can forget all about my pain, and \nsmile like I don't have a care in the world. \nBecause I'm <i>your</i> Fuji Kiseki."
    },
    {
      "name": "Fuji Kiseki",
      "text": "——And I want to stay your Fuji Kiseki… Forever."
    }
  ]
}