{
  "text_block_list": [
    {
      "name": "Nice Nature",
      "text": "Hey now, what's wrong, Tannhauser?\nYou're practically tearing your hair out."
    },
    {
      "name": "Nice Nature",
      "text": "Were you making some marvelous plans\nfor the school? Or do you want to practice\nsending letters by arrow? Whatever it is,\nI'm here to listen."
    },
    {
      "name": "Matikanetannhauser",
      "text": "Uuugh… Nature… I'm so worried about\nhow I did in the unit exam…"
    },
    {
      "name": "Nice Nature",
      "text": "…Hm."
    },
    {
      "name": "Nice Nature",
      "text": "That's a very normal concern."
    },
    {
      "name": "Matikanetannhauser",
      "text": "Ooh, but I'm so worried… The material\nin the exam was pretty difficult this time."
    },
    {
      "name": "Matikanetannhauser",
      "text": "I really hope I didn't fail again! Please don't\nmake me do any more extra lessons…!"
    },
    {
      "name": "Nice Nature",
      "text": "Ahh… this is so refreshing."
    },
    {
      "name": "Matikanetannhauser",
      "text": "What? What's so refreshing about this?!\nIf you know some secret way of calming\ndown, please teach meee!"
    }
  ],
  "no_wrap": true
}