{
  "text_block_list": [
    {
      "name": "Super Creek",
      "text": "Oh, Inari — here's something\nthat might interest you."
    },
    {
      "name": "Super Creek",
      "text": "While I was out and about earlier,\nI saw a portable shrine."
    },
    {
      "name": "Super Creek",
      "text": "So I think there must be\na local festival going on."
    },
    {
      "name": "Inari One",
      "text": "Really? That's what this Edo girl likes to hear!\nI've gotta get involved!"
    },
    {
      "name": "Super Creek",
      "text": "Oh, um… Are you thinking of\ncarrying the shrine?"
    },
    {
      "name": "Inari One",
      "text": "'Course I am! The shrine's the centerpiece\nof a festival!"
    },
    {
      "name": "Super Creek",
      "text": "I'm worried, though. It was so large…"
    },
    {
      "name": "Inari One",
      "text": "What're you talkin' about? I can lift a portable\nshrine or two any day of the—"
    },
    {
      "name": "Super Creek",
      "text": "…But won't the other carriers lift you up\nalong with the shrine?"
    },
    {
      "name": "Inari One",
      "text": "<i>That's</i> what you're worried about?!"
    }
  ],
  "no_wrap": true
}