{
    "no_wrap": true,
    "text_block_list": [
        {
            "name": "Jungle Pocket",
            "text": "——Doesn't matter who it is. \nWe fight anyone strong. \nThat's how we L/Roars roll."
        },
        {
            "name": "Jungle Pocket",
            "text": "This upcoming race—I'll \nbe there. I'll break their spirits \nwith my running."
        },
        {
            "name": "Jungle Pocket",
            "text": "…Heh. Aight, see ya later. \nGot something small to \ntake care of on my end."
        },
        {
            "name": "Jungle Pocket",
            "text": "…Oh! Trainer! You hear \n'bout the news?"
        },
        {
            "name": "Jungle Pocket",
            "text": "Cafeteria's got 3 limited-time parfaits \non sale right now! Wanna go? \nLike right now? Hey?! C'mon!"
        }
    ]
}