{
  "text_block_list": [
    {
      "name": "Air Shakur",
      "text": "What? I'm hungry, so I'm eating. Duh."
    },
    {
      "name": "Air Shakur",
      "text": "I'm guessing you want me to eat a \"real meal\"\nor whatever, but supplements and cereal just\nget the job done more efficiently."
    },
    {
      "name": "Air Shakur",
      "text": "As long as I get my nutrients, it doesn't \nmatter what I eat. I mean, if it tastes good \nthen cool, but that's not what matters \nmost to ——"
    },
    {
      "name": "Air Shakur",
      "text": "…Forget it. I yapped too much… <i>Tch</i>."
    }
  ],
  "no_wrap": true
}